pokime/__init__.py
pokime/pokime.py
pokime/pokime_helpers.py
pokime-0.1.1.dist-info/licenses/LICENSE
pokime-0.1.1.dist-info/METADATA
pokime-0.1.1.dist-info/WHEEL
pokime-0.1.1.dist-info/entry_points.txt
pokime-0.1.1.dist-info/top_level.txt
pokime-0.1.1.dist-info/RECORD
