Metadata-Version: 2.4
Name: pokime
Version: 0.1.1
Summary: MCP server that gives information on Anime and Pokemon
Author-email: harsh_buddhdev <harshbuddhdev5@gmail.com>
License: MIT
Classifier: Programming Language :: Python :: 3
Classifier: License :: OSI Approved :: MIT License
Classifier: Operating System :: OS Independent
Requires-Python: >=3.10
License-File: LICENSE
Requires-Dist: mcp>=1.2.0
Requires-Dist: requests
Dynamic: license-file
